isqlite/__init__.py
isqlite/_core.py
isqlite/_exception.py
isqlite/cli.py
isqlite/columns.py
isqlite/core.py
isqlite/database.py
isqlite/exceptions.py
isqlite/macros.py
isqlite/main.py
isqlite/migrations.py
isqlite/query.py
isqlite/schema.py
isqlite/utils.py
isqlite-1.6.0.dist-info/LICENSE
isqlite-1.6.0.dist-info/METADATA
isqlite-1.6.0.dist-info/WHEEL
isqlite-1.6.0.dist-info/entry_points.txt
isqlite-1.6.0.dist-info/top_level.txt
isqlite-1.6.0.dist-info/RECORD
