Metadata-Version: 2.1
Name: isqlite
Version: 1.6.0
Summary: An improved Python interface to SQLite
Home-page: UNKNOWN
Author: Ian Fisher
Author-email: iafisher@fastmail.com
License: MIT
Project-URL: Source, https://github.com/iafisher/isqlite
Platform: UNKNOWN
Classifier: Programming Language :: Python :: 3
Classifier: Programming Language :: SQL
Classifier: License :: OSI Approved :: MIT License
Classifier: Natural Language :: English
Classifier: Topic :: Database
Requires-Dist: click (>=8.0.0)
Requires-Dist: sqliteparser (>=0.5.4)
Requires-Dist: tabulate (>=0.8.9)
